muacrypt/__init__.py
muacrypt/account.py
muacrypt/bingpg.py
muacrypt/bot.py
muacrypt/chainstore.py
muacrypt/cmdline.py
muacrypt/cmdline_utils.py
muacrypt/hookspec.py
muacrypt/mime.py
muacrypt/myattr.py
muacrypt/recommendation.py
muacrypt/states.py
muacrypt/testing_plugin.py
muacrypt-0.9.1.dist-info/DESCRIPTION.rst
muacrypt-0.9.1.dist-info/LICENSE.txt
muacrypt-0.9.1.dist-info/METADATA
muacrypt-0.9.1.dist-info/RECORD
muacrypt-0.9.1.dist-info/WHEEL
muacrypt-0.9.1.dist-info/entry_points.txt
muacrypt-0.9.1.dist-info/metadata.json
muacrypt-0.9.1.dist-info/top_level.txt
test_muacrypt/__init__.py
test_muacrypt/sendbotmail.py
test_muacrypt/test_account.py
test_muacrypt/test_bingpg.py
test_muacrypt/test_bot.py
test_muacrypt/test_chainstore.py
test_muacrypt/test_cmdline.py
test_muacrypt/test_hooks.py
test_muacrypt/test_mime.py
test_muacrypt/test_recommendation.py
test_muacrypt/test_states.py
