Metadata-Version: 2.0
Name: muacrypt
Version: 0.9.1
Summary: support tool and API for Autocrypt mail agents
Home-page: https://muacrypt.readthedocs.io
Author: holger krekel and the muacrypt team
Author-email: holger@merlinux.eu
License: MIT license
Platform: unix
Platform: linux
Platform: osx
Platform: cygwin
Platform: win32
Classifier: Development Status :: 3 - Alpha
Classifier: Intended Audience :: Developers
Classifier: License :: OSI Approved :: MIT License
Classifier: Operating System :: POSIX
Classifier: Operating System :: MacOS :: MacOS X
Classifier: Topic :: Utilities
Classifier: Intended Audience :: Developers
Classifier: Programming Language :: Python
Requires-Dist: attrs
Requires-Dist: click (>=6.0)
Requires-Dist: execnet
Requires-Dist: pluggy
Requires-Dist: six
Requires-Dist: termcolor
